kingsos_uploader/__init__.py
kingsos-0.1.dist-info/METADATA
kingsos-0.1.dist-info/WHEEL
kingsos-0.1.dist-info/top_level.txt
kingsos-0.1.dist-info/RECORD
