Metadata-Version: 2.1
Name: kingsos
Version: 0.1
Summary: A package to upload KingsOS Operating System
Author: KralMatko
Author-email: kingmartinv2015@gmail.com
